cloudflare/__init__.py
cloudflare/client.py
cloudflare/parser.py
cloudflare/test_client.py
cloudflare/test_parser.py
telegraf_cloudflare-0.2.3.data/scripts/telegraf-cloudflare
telegraf_cloudflare-0.2.3.dist-info/METADATA
telegraf_cloudflare-0.2.3.dist-info/RECORD
telegraf_cloudflare-0.2.3.dist-info/WHEEL
telegraf_cloudflare-0.2.3.dist-info/top_level.txt
