Metadata-Version: 2.1
Name: telegraf-cloudflare
Version: 0.2.3
Summary: Plugin for Telegraf for gathering statistics from Cloudflare
Home-page: https://github.com/SebastianCzoch/telegraf-cloudflare
Author: Sebastian Czoch
Author-email: sebastian@czoch.pl
License: MIT
Platform: UNKNOWN
Classifier: Development Status :: 4 - Beta
Classifier: Intended Audience :: System Administrators
Classifier: License :: OSI Approved :: MIT License
Classifier: Programming Language :: Python :: 2
Classifier: Operating System :: OS Independent
Requires-Dist: influx-line-protocol (>=0.1.0)
Requires-Dist: requests (>=2.19)
Requires-Dist: python-dateutil (>=2.7.3)
Requires-Dist: mock; python_version < "3.3"
